tplinkcloud/__init__.py
tplinkcloud/api_response.py
tplinkcloud/client.py
tplinkcloud/device.py
tplinkcloud/device_client.py
tplinkcloud/device_info.py
tplinkcloud/device_manager.py
tplinkcloud/device_manager_power_tools.py
tplinkcloud/device_net_info.py
tplinkcloud/device_schedule_rule_builder.py
tplinkcloud/device_schedule_rules.py
tplinkcloud/device_time.py
tplinkcloud/device_timezone.py
tplinkcloud/device_type.py
tplinkcloud/emeter_device.py
tplinkcloud/ep40.py
tplinkcloud/ep40_child.py
tplinkcloud/hs100.py
tplinkcloud/hs103.py
tplinkcloud/hs105.py
tplinkcloud/hs110.py
tplinkcloud/hs300.py
tplinkcloud/hs300_child.py
tplinkcloud/kp115.py
tplinkcloud/kp125.py
tplinkcloud/kp303.py
tplinkcloud/kp303_child.py
tplink_cloud_api-4.2.0.dist-info/LICENSE
tplink_cloud_api-4.2.0.dist-info/METADATA
tplink_cloud_api-4.2.0.dist-info/WHEEL
tplink_cloud_api-4.2.0.dist-info/top_level.txt
tplink_cloud_api-4.2.0.dist-info/RECORD
