Metadata-Version: 2.2
Name: tplink-cloud-api
Version: 4.2.0
Summary: Python library for communicating with the TP-Link Cloud API to manage TP-Link Kasa Smart Home devices
Home-page: https://github.com/piekstra/tplink-cloud-api
Author: Dev Piekstra
Author-email: piekstra.dev@gmail.com
License: GPL-3
Classifier: Programming Language :: Python :: 3
Classifier: License :: OSI Approved :: GNU General Public License v3 (GPLv3)
Classifier: Operating System :: OS Independent
Requires-Python: >=3.7
License-File: LICENSE
Requires-Dist: requests<3,>=2
Requires-Dist: aiohttp<4,>=3
Dynamic: author
Dynamic: author-email
Dynamic: classifier
Dynamic: description
Dynamic: description-content-type
Dynamic: home-page
Dynamic: license
Dynamic: requires-dist
Dynamic: requires-python
Dynamic: summary
